tno/quantum/ml/classifiers/svm/__init__.py
tno/quantum/ml/classifiers/svm/_support_vector_machine.py
tno/quantum/ml/classifiers/svm/kernels.py
tno/quantum/ml/classifiers/svm/py.typed
tno/quantum/ml/classifiers/svm/assets/example.png
tno/quantum/ml/classifiers/svm/test/__init__.py
tno/quantum/ml/classifiers/svm/test/test_kernels.py
tno/quantum/ml/classifiers/svm/test/test_support_vector_machine.py
tno_quantum_ml_classifiers_svm-2.0.2.dist-info/licenses/LICENSE
tno_quantum_ml_classifiers_svm-2.0.2.dist-info/METADATA
tno_quantum_ml_classifiers_svm-2.0.2.dist-info/WHEEL
tno_quantum_ml_classifiers_svm-2.0.2.dist-info/top_level.txt
tno_quantum_ml_classifiers_svm-2.0.2.dist-info/RECORD
