Metadata-Version: 2.4
Name: tno.quantum.ml.classifiers.svm
Version: 2.0.2
Summary: Support Vector Machine Classifier
Author-email: TNO Quantum Code Lab <tnoquantum@tno.nl>
Maintainer-email: TNO Quantum Code Lab <tnoquantum@tno.nl>
License: Apache License, Version 2.0
Project-URL: Homepage, https://github.com/TNO-Quantum/
Project-URL: Documentation, https://github.com/TNO-Quantum/
Project-URL: Source, https://ci.tno.nl/gitlab/quantum/quantum-applications/quantum-toolbox/microlibs/machine-learning/microlibs/classifiers/microlibs/svm
Keywords: Support Vector Machine,Quantum,SVM,Machine Learning,Classifier
Platform: any
Classifier: License :: OSI Approved :: Apache Software License
Classifier: Programming Language :: Python :: 3
Classifier: Programming Language :: Python :: 3.10
Classifier: Programming Language :: Python :: 3.11
Classifier: Programming Language :: Python :: 3.12
Classifier: Programming Language :: Python :: 3.13
Classifier: Operating System :: OS Independent
Classifier: Intended Audience :: Developers
Classifier: Intended Audience :: Information Technology
Classifier: Intended Audience :: Science/Research
Classifier: Typing :: Typed
Requires-Python: >=3.10
License-File: LICENSE
Requires-Dist: numpy
Requires-Dist: tno.quantum.ml.components~=2.0
Requires-Dist: tno.quantum.utils~=5.1
Requires-Dist: tno.quantum.optimization.qubo
Provides-Extra: example
Requires-Dist: tno.quantum.optimization.qubo[dwave]; extra == "example"
Requires-Dist: tno.quantum.ml.datasets; extra == "example"
Provides-Extra: tests
Requires-Dist: tno.quantum.ml.datasets~=2.0; extra == "tests"
Requires-Dist: pytest>=8.1.1; extra == "tests"
Requires-Dist: pytest-cov>=4.1.0; extra == "tests"
Requires-Dist: tno.quantum.optimization.qubo.solvers[dwave]; extra == "tests"
Dynamic: license-file
